<course>
<title>ФГОС СПО 13.02.03 МДК 03.01 Энергосберегающие мероприятия в системе освещения</title>
<description/>
<language>ru</language>
<!-- Что это? -->
<code>301121138</code> 
<!-- Что это? -->
<fgos_title>ФГОС СПО 13.02.03</fgos_title>
<fgos_text>Электрические станции, сети и системы
</fgos_text>
<mdk_title>МДК 03.01</mdk_title>
<mdk_text>Автоматизированные системы управления в электроэнергетических системах</mdk_text>
<structure>
<item0>
<name>Энергосберегающие мероприятия в системе освещения
</name>
<code>1_eom</code>
</item0>
<item1>
<name>Энергосберегающие мероприятия в системе освещения
</name>
<code>2_eom</code>
</item1>
<item2>
<name>Энергосберегающие мероприятия в системе освещения
</name>
<code>3_eom</code>
</item2>
</structure>
</course>
